CosmosChosen/__init__.py
CosmosChosen/_modidx.py
CosmosChosen/core.py
cosmos_chosen-0.0.1.dist-info/LICENSE
cosmos_chosen-0.0.1.dist-info/METADATA
cosmos_chosen-0.0.1.dist-info/WHEEL
cosmos_chosen-0.0.1.dist-info/entry_points.txt
cosmos_chosen-0.0.1.dist-info/top_level.txt
cosmos_chosen-0.0.1.dist-info/RECORD
