Metadata-Version: 2.1
Name: cosmos-chosen
Version: 0.0.1
Summary: 你的想法那么优秀，一定是天选吧！Your idea is so brilliant, it must be the chosen one!
Home-page: https://github.com/2catycm/CosmosChosen
Author: 叶璨铭
Author-email: 12011404@mail.sustech.edu.cn
License: Apache Software License 2.0
Keywords: nbdev jupyter notebook python
Platform: UNKNOWN
Classifier: Development Status :: 4 - Beta
Classifier: Intended Audience :: Developers
Classifier: Natural Language :: English
Classifier: Programming Language :: Python :: 3.7
Classifier: Programming Language :: Python :: 3.8
Classifier: Programming Language :: Python :: 3.9
Classifier: Programming Language :: Python :: 3.10
Classifier: Programming Language :: Python :: 3.11
Classifier: Programming Language :: Python :: 3.12
Classifier: License :: OSI Approved :: Apache Software License
Requires-Python: >=3.7
License-File: LICENSE
Provides-Extra: dev
